segmindapi/AllInOnePixel.py
segmindapi/BackgroundRemoval.py
segmindapi/Cartoon.py
segmindapi/Codeformer.py
segmindapi/Colorful.py
segmindapi/ControlNet.py
segmindapi/CuteRichStyle.py
segmindapi/CyberRealistic.py
segmindapi/DeepSpaceDiffusion.py
segmindapi/DreamShaper.py
segmindapi/DvArch.py
segmindapi/ESRGAN.py
segmindapi/EdgeOfRealism.py
segmindapi/EpicRealism.py
segmindapi/FaceSwap.py
segmindapi/FantassifiedIcons.py
segmindapi/Flat2D.py
segmindapi/FruitFusion.py
segmindapi/Icbinp.py
segmindapi/Juggernaut.py
segmindapi/Kadinsky.py
segmindapi/MajicMix.py
segmindapi/ManmaruMix.py
segmindapi/Mix526.py
segmindapi/Paragon.py
segmindapi/PortraitSD.py
segmindapi/QRGenerator.py
segmindapi/RCNZ.py
segmindapi/RPG.py
segmindapi/RealisticVision.py
segmindapi/Reliberate.py
segmindapi/Revanimated.py
segmindapi/SAM.py
segmindapi/SD1_5.py
segmindapi/SD2_1.py
segmindapi/SDOutpainting.py
segmindapi/SDXL.py
segmindapi/Samaritan.py
segmindapi/SciFi.py
segmindapi/SmallSD.py
segmindapi/T2I.py
segmindapi/TinySD.py
segmindapi/Word2Img.py
segmindapi/__init__.py
segmindapi/utils.py
segmindapi-0.3.0.dist-info/LICENSE.txt
segmindapi-0.3.0.dist-info/METADATA
segmindapi-0.3.0.dist-info/WHEEL
segmindapi-0.3.0.dist-info/top_level.txt
segmindapi-0.3.0.dist-info/RECORD
